{
  "code": 0,
  "shop_url": "https://15522634982.davdian.com",
  "visitor_status": 3,
  "sess_key": "42df8bf6e510c97c11afe81a96569014027bf803",
  "data": {
    "signDays":"12",
    "startMonth": "2017-08-18",
    "joinDays":"2",
    "dateInfo":{
      "1":"2",
      "2":"1",
      "3":"5"
    },
    "activity": {
      "type": "2",
      "list": [
        {
          "title": "string, 活动名称",
          "imageUrl": "http://9i.dvmama.com/supplier/2017/07/18/1000_1000_67ffb738c51b2f6f6e17231905197e2d.jpg?x-oss-process=image/resize,m_fill,w_640,h_640/format,webp",
          "desc": "string, 活动描述",
          "signStatus": "1",
          "actStatus": "2",
          "joinDays":"10",
          "actSignDays":"12"
        },
        {
          "title": "string, 活动名称",
          "imageUrl": "http://9i.dvmama.com/supplier/2017/07/18/1000_1000_67ffb738c51b2f6f6e17231905197e2d.jpg?x-oss-process=image/resize,m_fill,w_640,h_640/format,webp",
          "desc": "string, 活动描述",
          "signStatus": "2",
          "joinDays":"10",
          "actSignDays":"12"
        }
      ]
    }
  }
}
